CHANGELOG.md
LICENSE
ifpd2q/__init__.py
ifpd2q/asserts.py
ifpd2q/chromosome.py
ifpd2q/const.py
ifpd2q/database.py
ifpd2q/dataclasses.py
ifpd2q/fasta.py
ifpd2q/io.py
ifpd2q/loggingg.py
ifpd2q/oligo.py
ifpd2q/probe.py
ifpd2q/probe_set.py
ifpd2q/region.py
ifpd2q/scripts/__init__.py
ifpd2q/scripts/arguments.py
ifpd2q/scripts/autocomplete.py
ifpd2q/scripts/db/__init__.py
ifpd2q/scripts/db/check.py
ifpd2q/scripts/db/dump.py
ifpd2q/scripts/db/info.py
ifpd2q/scripts/db/make.py
ifpd2q/scripts/db/run.py
ifpd2q/scripts/db/settings.py
ifpd2q/scripts/extract_kmers.py
ifpd2q/scripts/ifpd2.py
ifpd2q/scripts/query.py
ifpd2q/scripts/query2.py
ifpd2q/tests/__init__.py
ifpd2q/tests/test_scripts_db.py
ifpd2q/walker.py
ifpd2q/walker2.py
ifpd2q-1.0.4.dist-info/LICENSE
ifpd2q-1.0.4.dist-info/METADATA
ifpd2q-1.0.4.dist-info/WHEEL
ifpd2q-1.0.4.dist-info/entry_points.txt
ifpd2q-1.0.4.dist-info/RECORD
