Metadata-Version: 2.1
Name: ifpd2q
Version: 1.0.4
Summary: An iFISH probe design pipeline (II)
Home-page: https://github.com/BiCro-HT/ifpd2_new
License: MIT
Keywords: biology,cell,DNA,RNA,FISH,fluorescence,hybridization
Author: Gabriele Girelli
Author-email: gigi.ga90@gmail.com
Maintainer: Quentin Verron
Requires-Python: >=3.8,<4.0
Classifier: Development Status :: 3 - Alpha
Classifier: Environment :: Console
Classifier: Intended Audience :: Science/Research
Classifier: License :: OSI Approved :: MIT License
Classifier: Operating System :: POSIX :: Linux
Classifier: Operating System :: Unix
Classifier: Programming Language :: Python :: 3
Classifier: Programming Language :: Python :: 3.8
Classifier: Programming Language :: Python :: 3.9
Classifier: Programming Language :: Python :: 3.10
Classifier: Programming Language :: Python :: 3.11
Classifier: Programming Language :: Python :: 3.12
Classifier: Topic :: Scientific/Engineering :: Bio-Informatics
Classifier: Typing :: Typed
Requires-Dist: biopython (>=1.79,<2.0)
Requires-Dist: click (>=8.0.1,<9.0.0)
Requires-Dist: numpy (>=1.20.1,<2.0.0)
Requires-Dist: pandas (>=1.5.3,<3.0.0)
Requires-Dist: rich (>=9.10,<11.0)
Requires-Dist: tqdm (>=4.58.0,<5.0.0)
Project-URL: Repository, https://github.com/BiCro-HT/ifpd2_new
